gwaslab/__init__.py
gwaslab/__main__.py
gwaslab/cache_manager.py
gwaslab/g_Sumstats.py
gwaslab/g_SumstatsMulti.py
gwaslab/g_SumstatsPair.py
gwaslab/g_SumstatsSet.py
gwaslab/g_SumstatsT.py
gwaslab/g_Sumstats_polars.py
gwaslab/CLI/cli.py
gwaslab/bd/bd_build.py
gwaslab/bd/bd_chromosome_mapper.py
gwaslab/bd/bd_common_data.py
gwaslab/bd/bd_config.py
gwaslab/bd/bd_download.py
gwaslab/bd/bd_get_hapmap3.py
gwaslab/bd/bd_path_manager.py
gwaslab/bd/bd_sex_chromosomes.py
gwaslab/data/config.json
gwaslab/data/formatbook.json
gwaslab/data/reference.json
gwaslab/data/chains/hg19ToHg38.over.chain.gz
gwaslab/data/chains/hg38ToHg19.over.chain.gz
gwaslab/data/chromosomes/chromosomes_nc.json
gwaslab/data/chrx_par/chrx_par_hg19.bed.gz
gwaslab/data/chrx_par/chrx_par_hg38.bed.gz
gwaslab/data/cytoband/cytoBand_hg19.txt.gz
gwaslab/data/cytoband/cytoBand_hg38.txt.gz
gwaslab/data/hapmap3_SNPs/hapmap3_db150_hg19.snplist.gz
gwaslab/data/hapmap3_SNPs/hapmap3_db151_hg38.snplist.gz
gwaslab/data/high_ld/high_ld_hla_hg19.bed.gz
gwaslab/data/high_ld/high_ld_hla_hg38.bed.gz
gwaslab/downstream/__init__.py
gwaslab/downstream/ds_result_manager.py
gwaslab/extension/__init__.py
gwaslab/extension/extension_version.py
gwaslab/extension/gwas_sumstats_tools/validate_ssf.py
gwaslab/extension/gwascatalog/__init__.py
gwaslab/extension/gwascatalog/gwascatalog.py
gwaslab/extension/ldsc/ldsc_irwls.py
gwaslab/extension/ldsc/ldsc_jackknife.py
gwaslab/extension/ldsc/ldsc_ldscore.py
gwaslab/extension/ldsc/ldsc_parse.py
gwaslab/extension/ldsc/ldsc_regressions.py
gwaslab/extension/ldsc/ldsc_sumstats.py
gwaslab/extension/prscs/precs_mcmc_gtb2.py
gwaslab/extension/prscs/prscs_gigrnd.py
gwaslab/extension/prscs/prscs_gigrnd2.py
gwaslab/extension/prscs/prscs_mcmc_gtb.py
gwaslab/extension/prscs/prscs_parse_genet.py
gwaslab/hm/hm_assign_rsid.py
gwaslab/hm/hm_casting.py
gwaslab/hm/hm_casting_polars.py
gwaslab/hm/hm_check_af.py
gwaslab/hm/hm_harmonize_sumstats.py
gwaslab/hm/hm_infer_with_af.py
gwaslab/hm/hm_liftover_v2.py
gwaslab-4.0.4.dist-info/licenses/LICENSE
gwaslab-4.0.4.dist-info/METADATA
gwaslab-4.0.4.dist-info/WHEEL
gwaslab-4.0.4.dist-info/entry_points.txt
gwaslab-4.0.4.dist-info/top_level.txt
gwaslab-4.0.4.dist-info/RECORD
