Metadata-Version: 2.4
Name: gwaslab
Version: 4.0.4
Summary: Python toolkit for handling GWAS summary statistics
Author-email: Yunye He <gwaslab@gmail.com>
License: GPL-3.0-only
Project-URL: Homepage, https://cloufield.github.io/gwaslab/
Project-URL: Repository, https://github.com/Cloufield/gwaslab
Requires-Python: >=3.9
License-File: LICENSE
Requires-Dist: pandas!=1.5,>=1.3
Requires-Dist: numpy<2,>=1.21.2
Requires-Dist: matplotlib<3.9,>=3.8
Requires-Dist: seaborn>=0.12
Requires-Dist: scipy>=1.12
Requires-Dist: pysam==0.22.1
Requires-Dist: adjustText<=0.8,>=0.7.3
Requires-Dist: scikit-allel>=1.3.5
Requires-Dist: h5py>=3.10.0
Requires-Dist: pyarrow
Requires-Dist: polars>=1.27.0
Requires-Dist: sumstats-liftover==1.1.0
Requires-Dist: requests
Requires-Dist: pyyaml
Requires-Dist: bitarray
Requires-Dist: platformdirs
Dynamic: license-file
